MCTS/DFMCS.py
MCTS/MCTS.py
MCTS/__init__.py
MCTS/integrate.py
MCTS/net.py
MCTS/test.py
MCTS/utils.py
MCTS_DUT/DFMCS.py
MCTS_DUT/MCTS.py
MCTS_DUT/__init__.py
MCTS_DUT/integrate.py
MCTS_DUT/net.py
MCTS_DUT/test.py
MCTS_DUT/utils.py
dut-sar/DFMCS.py
dut-sar/MCTS.py
dut-sar/__init__.py
dut-sar/integrate.py
dut-sar/net.py
dut-sar/test.py
dut-sar/utils.py
dutSar/DFMCS.py
dutSar/MCTS.py
dutSar/__init__.py
dutSar/integrate.py
dutSar/net.py
dutSar/test.py
dutSar/uplaod.py
dutSar/utils.py
dutSarImage/DFMCS.py
dutSarImage/MCTS.py
dutSarImage/__init__.py
dutSarImage/integrate.py
dutSarImage/net.py
dutSarImage/test.py
dutSarImage/uplaod.py
dutSarImage/utils.py
dut_sar/DFMCS.py
dut_sar/MCTS.py
dut_sar/__init__.py
dut_sar/integrate.py
dut_sar/net.py
dut_sar/test.py
dut_sar/uplaod.py
dut_sar/utils.py
dutSarImage-2.1.1.dist-info/LICENSE
dutSarImage-2.1.1.dist-info/METADATA
dutSarImage-2.1.1.dist-info/WHEEL
dutSarImage-2.1.1.dist-info/entry_points.txt
dutSarImage-2.1.1.dist-info/top_level.txt
dutSarImage-2.1.1.dist-info/RECORD
