Metadata-Version: 2.1
Name: dutSarImage
Version: 2.1.1
Summary: Algorithms for blackbox falsification of convolutional neural networks
Author: Qyy
Keywords: testing,safety,deep learning,computer vision
License-File: LICENSE
